pycolorana/__init__.py
pycolorana/ansi.py
pycolorana/colors.py
pycolorana/core.py
pycolorana/styles.py
pycolorana/terminal.py
pycolorana/utils.py
pycolorana/win32.py
pycolorana/winterm.py
pycolorana-1.2.dist-info/LICENSE.txt
pycolorana-1.2.dist-info/METADATA
pycolorana-1.2.dist-info/WHEEL
pycolorana-1.2.dist-info/top_level.txt
pycolorana-1.2.dist-info/RECORD
